STHD/__init__.py
STHD/binning.py
STHD/binning_fast.py
STHD/color_palette.py
STHD/config.py
STHD/frontline.py
STHD/hdpp.py
STHD/model.py
STHD/patchify.py
STHD/qcmask.py
STHD/refscrna.py
STHD/roi.py
STHD/sim.py
STHD/sthdio.py
STHD/sthdviz.py
STHD/train.py
STHD/viz.py
sthd-1.0.1.dist-info/METADATA
sthd-1.0.1.dist-info/WHEEL
sthd-1.0.1.dist-info/licenses/LICENSE
sthd-1.0.1.dist-info/RECORD
