Metadata-Version: 2.4
Name: STHD
Version: 1.0.1
Summary: STHD: probabilistic cell typing of single Spots in whole Transcriptome spatial data with High Definition
Project-URL: Authors, https://yi-zhang-compbio-lab.github.io/
Project-URL: Documentation, https://readthedocs.org
Project-URL: Repository, https://github.com/yi-zhang/STHD.git
Author-email: Yi Zhang <yi.zhang@duke.edu>
License: 
License-File: LICENSE
Keywords: machine learning,single-cell genomics,spatial transcriptomics
Requires-Python: >=3.8.0
Requires-Dist: anndata>=0.9.2
Requires-Dist: bokeh>=3.1.1
Requires-Dist: matplotlib
Requires-Dist: numba>=0.55.2
Requires-Dist: numpy
Requires-Dist: pandas
Requires-Dist: scanpy>=1.9.8
Requires-Dist: scipy
Requires-Dist: squidpy>=1.2.3
Requires-Dist: tifffile>=2023.7.10
Requires-Dist: tqdm>=4.66.4
